sample_api_client/__init__.py
sample_api_client/api/__init__.py
sample_api_client/api/default/__init__.py
sample_api_client/api/default/get_users.py
sample_api_client/client.py
sample_api_client/models/__init__.py
sample_api_client/py.typed
sample_api_client/types.py
sample_api_client-0.1.9.dist-info/WHEEL
sample_api_client-0.1.9.dist-info/METADATA
sample_api_client-0.1.9.dist-info/RECORD
