Metadata-Version: 2.1
Name: sample-api-client
Version: 0.1.9
Summary: A client library for accessing Sample API
Requires-Python: >=3.6,<4.0
Classifier: Programming Language :: Python :: 3
Classifier: Programming Language :: Python :: 3.6
Classifier: Programming Language :: Python :: 3.7
Classifier: Programming Language :: Python :: 3.8
Classifier: Programming Language :: Python :: 3.9
Requires-Dist: attrs (>=20.1.0,<21.0.0)
Requires-Dist: httpx (>=0.15.0,<0.16.0)
Requires-Dist: python-dateutil (>=2.8.1,<3.0.0)
